Metadata-Version: 1.1
Name: malupdate
Version: 0.4.1
Summary: Package to interact with MyAnimeList using the Official API
Home-page: https://github.com/m0mosenpai/malupdate
Author: Sarthak Khattar
Author-email: sarthakoct@gmail.com
License: UNKNOWN
Download-URL: https://github.com/m0mosenpai/malupdate/archive/v0.4.1.tar.gz
Keywords: MAL API Script
Platform: UNKNOWN
Classifier: Development Status :: 3 - Alpha
Classifier: Intended Audience :: Developers
Classifier: Topic :: Software Development :: Build Tools
Classifier: License :: OSI Approved :: MIT License
Classifier: Programming Language :: Python :: 3
Classifier: Programming Language :: Python :: 3.4
Classifier: Programming Language :: Python :: 3.5
Classifier: Programming Language :: Python :: 3.6
